pyhoff/__init__.py
pyhoff/devices.py
pyhoff/modbus.py
pyhoff/py.typed
pyhoff-1.1.2.dist-info/licenses/LICENSE
pyhoff-1.1.2.dist-info/METADATA
pyhoff-1.1.2.dist-info/WHEEL
pyhoff-1.1.2.dist-info/top_level.txt
pyhoff-1.1.2.dist-info/RECORD
