Metadata-Version: 2.4
Name: pyhoff
Version: 1.1.2
Summary: The pyhoff package allows easy accessing of Beckhoff and Wago terminals with python over ModBus TCP
Author-email: Nicolas Kruse <nicolas.kruse@nonan.net>
License-Expression: MIT
Project-URL: Homepage, https://github.com/Nonannet/pyhoff
Project-URL: Issues, https://github.com/Nonannet/pyhoff/issues
Project-URL: documentation, https://nonannet.github.io/pyhoff/
Classifier: Programming Language :: Python :: 3
Classifier: Operating System :: OS Independent
Requires-Python: >=3.10
License-File: LICENSE
Provides-Extra: dev
Requires-Dist: pytest; extra == "dev"
Requires-Dist: flake8; extra == "dev"
Requires-Dist: mypy; extra == "dev"
Provides-Extra: doc-build
Requires-Dist: sphinx; extra == "doc-build"
Requires-Dist: pydata_sphinx_theme; extra == "doc-build"
Requires-Dist: sphinx-autodoc-typehints; extra == "doc-build"
Requires-Dist: myst-parser; extra == "doc-build"
Dynamic: license-file
